mrcz/ReliablePy.py
mrcz/__init__.py
mrcz/__version__.py
mrcz/ioDM.py
mrcz/ioMRC.py
mrcz/test_mrcz.py
mrcz-0.5.7.dist-info/AUTHORS.txt
mrcz-0.5.7.dist-info/LICENSE.txt
mrcz-0.5.7.dist-info/METADATA
mrcz-0.5.7.dist-info/WHEEL
mrcz-0.5.7.dist-info/top_level.txt
mrcz-0.5.7.dist-info/RECORD
