Metadata-Version: 2.1
Name: mrcz
Version: 0.5.7
Summary: MRCZ meta-compressed image file-format library
Home-page: http://github.com/em-MRCZ/python-mrcz
Author: Robert A. McLeod, Ricardo Righetto
Author-email: robbmcleod@gmail.com
License: https://opensource.org/licenses/BSD-3-Clause
Platform: any
Classifier: Development Status :: 4 - Beta
Classifier: Intended Audience :: Developers
Classifier: Intended Audience :: Information Technology
Classifier: Intended Audience :: Science/Research
Classifier: License :: OSI Approved :: BSD License
Classifier: Programming Language :: Python
Classifier: Programming Language :: Python :: 2.7
Classifier: Programming Language :: Python :: 3.5
Classifier: Programming Language :: Python :: 3.6
Classifier: Programming Language :: Python :: 3.7
Classifier: Programming Language :: Python :: 3.8
Classifier: Topic :: Software Development :: Libraries :: Python Modules
Classifier: Topic :: System :: Archiving :: Compression
Classifier: Operating System :: Microsoft :: Windows
Classifier: Operating System :: Unix
License-File: LICENSE.txt
License-File: AUTHORS.txt
Requires-Dist: numpy
